tkinter_colored_logging_handlers/__init__.py
tkinter_colored_logging_handlers/main.py
tkinter_colored_logging_handlers/py.typed
tkinter_colored_logging_handlers-0.0.4.dist-info/licenses/LICENSE
tkinter_colored_logging_handlers-0.0.4.dist-info/METADATA
tkinter_colored_logging_handlers-0.0.4.dist-info/WHEEL
tkinter_colored_logging_handlers-0.0.4.dist-info/top_level.txt
tkinter_colored_logging_handlers-0.0.4.dist-info/RECORD
