Metadata-Version: 2.4
Name: tkinter_colored_logging_handlers
Version: 0.0.4
Summary: Tkinker Logger
Home-page: https://github.com/fa0311/tkinter_colored_logging_handlers
Author: yuki
Author-email: yuki@yuki0311.com
License: MIT
Keywords: tkinter,logging,handler
License-File: LICENSE
Dynamic: author
Dynamic: author-email
Dynamic: description
Dynamic: description-content-type
Dynamic: home-page
Dynamic: keywords
Dynamic: license
Dynamic: license-file
Dynamic: summary
